{
    "$schema": "http://json-schema.org/draft-07/schema",
    "$id": "https://met.gov.bc.ca/.well_known/schemas/engagement_translation",
    "type": "object",
    "title": "The root schema",
    "description": "The root schema comprises the entire JSON document.",
    "default": {},
    "examples": [
      {
        "engagement_id": 1,
        "language_id": 1
      }
    ],
    "required": ["engagement_id", "language_id"],
    "properties": {
      "engagement_id": {
        "$id": "#/properties/engagement_id",
        "type": "number",
        "title": "engagement id",
        "description": "The engagement to which this translation belongs.",
        "examples": [1]
      },
      "language_id": {
        "$id": "#/properties/language_id",
        "type": "number",
        "title": "Language id",
        "description": "The language to which this translation belongs.",
        "examples": [1]
      }
    }
  }
